setup.py
distributions_gaussianbinomial_sss/Binomialdistribution.py
distributions_gaussianbinomial_sss/Gaussiandistribution.py
distributions_gaussianbinomial_sss/Generaldistribution.py
distributions_gaussianbinomial_sss/__init__.py
distributions_gaussianbinomial_sss.egg-info/PKG-INFO
distributions_gaussianbinomial_sss.egg-info/SOURCES.txt
distributions_gaussianbinomial_sss.egg-info/dependency_links.txt
distributions_gaussianbinomial_sss.egg-info/not-zip-safe
distributions_gaussianbinomial_sss.egg-info/top_level.txt